{
  "last_updated": "2026-04-25T21:51:43.198Z",
  "servers": [
    {
      "name": "Arkenstone",
      "status": "Online",
      "pop": "Alta",
      "type": "Standard"
    },
    {
      "name": "Brandywine",
      "status": "Online",
      "pop": "Alta",
      "type": "Standard"
    },
    {
      "name": "Crickhollow",
      "status": "Online",
      "pop": "Alta",
      "type": "Standard"
    },
    {
      "name": "Gladden",
      "status": "Online",
      "pop": "Alta",
      "type": "Standard"
    },
    {
      "name": "Landroval",
      "status": "Online",
      "pop": "Alta",
      "type": "Standard"
    },
    {
      "name": "Belegaer",
      "status": "Online",
      "pop": "Alta",
      "type": "Standard"
    },
    {
      "name": "Evernight",
      "status": "Online",
      "pop": "Alta",
      "type": "Standard"
    },
    {
      "name": "Gwaihir",
      "status": "Online",
      "pop": "Alta",
      "type": "Standard"
    },
    {
      "name": "Laurelin",
      "status": "Online",
      "pop": "Alta",
      "type": "Standard"
    },
    {
      "name": "Sirannon",
      "status": "Online",
      "pop": "Alta",
      "type": "Standard"
    },
    {
      "name": "Angmar",
      "status": "Online",
      "pop": "Alta",
      "type": "Legendary"
    },
    {
      "name": "Mordor",
      "status": "Online",
      "pop": "Alta",
      "type": "Legendary"
    },
    {
      "name": "Glamdring",
      "status": "Online",
      "pop": "Alta",
      "type": "Standard"
    },
    {
      "name": "Sting",
      "status": "Online",
      "pop": "Alta",
      "type": "Standard"
    },
    {
      "name": "Orcrist",
      "status": "Online",
      "pop": "Alta",
      "type": "Standard"
    }
  ],
  "steam_data": [
    [
      1776981929000,
      334
    ],
    [
      1776985593000,
      316
    ],
    [
      1776989208000,
      748
    ],
    [
      1776992724000,
      921
    ],
    [
      1776996372000,
      950
    ],
    [
      1776999920000,
      861
    ],
    [
      1777003515000,
      787
    ],
    [
      1777007070000,
      712
    ],
    [
      1777010713000,
      709
    ],
    [
      1777014319000,
      747
    ],
    [
      1777018033000,
      798
    ],
    [
      1777021545000,
      852
    ],
    [
      1777025195000,
      909
    ],
    [
      1777028836000,
      945
    ],
    [
      1777032407000,
      1020
    ],
    [
      1777036012000,
      1116
    ],
    [
      1777039578000,
      1248
    ],
    [
      1777043226000,
      1326
    ],
    [
      1777046833000,
      1393
    ],
    [
      1777050433000,
      1475
    ],
    [
      1777053937000,
      1622
    ],
    [
      1777057597000,
      1686
    ],
    [
      1777061166000,
      1674
    ],
    [
      1777064814000,
      1536
    ],
    [
      1777068412000,
      1302
    ],
    [
      1777072008000,
      1144
    ],
    [
      1777075525000,
      1094
    ],
    [
      1777079131000,
      1075
    ],
    [
      1777082757000,
      1033
    ],
    [
      1777086403000,
      966
    ],
    [
      1777090011000,
      889
    ],
    [
      1777093521000,
      868
    ],
    [
      1777097119000,
      867
    ],
    [
      1777100812000,
      941
    ],
    [
      1777104429000,
      1046
    ],
    [
      1777108087000,
      1104
    ],
    [
      1777111537000,
      1143
    ],
    [
      1777115197000,
      1190
    ],
    [
      1777118886000,
      1349
    ],
    [
      1777122397000,
      1475
    ],
    [
      1777125974000,
      1559
    ],
    [
      1777129631000,
      1651
    ],
    [
      1777133155000,
      1657
    ],
    [
      1777136825000,
      1747
    ],
    [
      1777140436000,
      1881
    ],
    [
      1777143677000,
      2018
    ],
    [
      1777147619000,
      1972
    ],
    [
      1777151215000,
      1795
    ]
  ],
  "live_players": 1735,
  "outage_message": null,
  "outage_link": null,
  "is_down": false
}